tmf882x/__init__.py
tmf882x/_version.py
tmf882x/constants.py
tmf882x/firmware.bin
tmf882x/measurement.py
tmf882x/py.typed
tmf882x_driver-0.2.0.dist-info/licenses/LICENSE
tmf882x_driver-0.2.0.dist-info/METADATA
tmf882x_driver-0.2.0.dist-info/WHEEL
tmf882x_driver-0.2.0.dist-info/top_level.txt
tmf882x_driver-0.2.0.dist-info/RECORD
