Metadata-Version: 2.4
Name: tmf882x-driver
Version: 0.2.0
Summary: Python driver for the AMS TMF8820/TMF8821 dToF imager
Author-email: Rogier van der Geer <rogier@vander-geer.nl>
Project-URL: Repository, https://github.com/rogiervandergeer/tmf882x-driver
Classifier: Programming Language :: Python :: 3
Classifier: License :: OSI Approved :: MIT License
Classifier: Topic :: System :: Hardware :: Hardware Drivers
Classifier: Typing :: Typed
License-File: LICENSE
Requires-Dist: smbus2>=0.3.0
Provides-Extra: dev
Requires-Dist: pytest; extra == "dev"
Dynamic: license-file
